zhmiscellanyocr/__init__.py
zhmiscellanyocr/_ocr_supportfuncs.py
zhmiscellanyocr/_py_resources.py
zhmiscellanyocr/_resource_files_lookup.py
zhmiscellanyocr-0.2.0.dist-info/METADATA
zhmiscellanyocr-0.2.0.dist-info/WHEEL
zhmiscellanyocr-0.2.0.dist-info/top_level.txt
zhmiscellanyocr-0.2.0.dist-info/RECORD
