Metadata-Version: 2.4
Name: zhmiscellanyocr
Version: 0.2.0
Summary: A collection of OCR (image text recognition) python functions made by zh.
Home-page: https://discord.gg/ThBBAuueVJ
Author: zh
Author-email: imnotgivingmyemailjustaddmeondiscordmydiscordisz_h_@zh.com
Project-URL: Bug Tracker, https://github.com/zen-ham/zhmiscellanyocr/issues
Classifier: Programming Language :: Python :: 3
Classifier: License :: OSI Approved :: MIT License
Classifier: Operating System :: Microsoft :: Windows
Requires-Python: >=3.6
Requires-Dist: pytesseract>=0
Requires-Dist: zhmiscellany>=0
